wwwgetpy/__init__.py
wwwgetpy/core.py
wwwgetpy-0.1.1.dist-info/LICENSE
wwwgetpy-0.1.1.dist-info/METADATA
wwwgetpy-0.1.1.dist-info/WHEEL
wwwgetpy-0.1.1.dist-info/top_level.txt
wwwgetpy-0.1.1.dist-info/RECORD
